scrapy_impersonate/__init__.py
scrapy_impersonate/handler.py
scrapy_impersonate/middleware.py
scrapy_impersonate/parser.py
scrapy_impersonate-1.6.2.dist-info/licenses/LICENSE
scrapy_impersonate-1.6.2.dist-info/METADATA
scrapy_impersonate-1.6.2.dist-info/WHEEL
scrapy_impersonate-1.6.2.dist-info/top_level.txt
scrapy_impersonate-1.6.2.dist-info/RECORD
