Metadata-Version: 2.4
Name: scrapy-impersonate
Version: 1.6.2
Summary: Scrapy download handler that can impersonate browser fingerprints
Home-page: https://github.com/jxlil/scrapy-impersonate
Author: Jalil SA (jxlil)
License: MIT
Classifier: Programming Language :: Python :: 3
Classifier: Programming Language :: Python :: 3.8
Classifier: Programming Language :: Python :: 3.9
Classifier: Programming Language :: Python :: 3.10
Classifier: Programming Language :: Python :: 3.11
Classifier: License :: OSI Approved :: MIT License
Requires-Python: >=3.8
License-File: LICENSE
Requires-Dist: curl-cffi>=0.13.0
Requires-Dist: scrapy>=2.12.0
Dynamic: author
Dynamic: classifier
Dynamic: description
Dynamic: description-content-type
Dynamic: home-page
Dynamic: license
Dynamic: license-file
Dynamic: requires-dist
Dynamic: requires-python
Dynamic: summary
